ProblemSolvingWithAlgorithmsAndDataStructureUsingPythonZhongwenban/README.md
ProblemSolvingWithAlgorithmsAndDataStructureUsingPythonZhongwenban/__init__.py
ProblemSolvingWithAlgorithmsAndDataStructureUsingPythonZhongwenban/__main__.py
ProblemSolvingWithAlgorithmsAndDataStructureUsingPythonZhongwenban/file.epub
ProblemSolvingWithAlgorithmsAndDataStructureUsingPythonZhongwenban/index.html
ProblemSolvingWithAlgorithmsAndDataStructureUsingPythonZhongwenban/css/__init__.py
ProblemSolvingWithAlgorithmsAndDataStructureUsingPythonZhongwenban/css/annotations.css
ProblemSolvingWithAlgorithmsAndDataStructureUsingPythonZhongwenban/css/main.css
ProblemSolvingWithAlgorithmsAndDataStructureUsingPythonZhongwenban/css/normalize.css
ProblemSolvingWithAlgorithmsAndDataStructureUsingPythonZhongwenban/css/popup.css
ProblemSolvingWithAlgorithmsAndDataStructureUsingPythonZhongwenban/font/__init__.py
ProblemSolvingWithAlgorithmsAndDataStructureUsingPythonZhongwenban/font/fontello.eot
ProblemSolvingWithAlgorithmsAndDataStructureUsingPythonZhongwenban/font/fontello.svg
ProblemSolvingWithAlgorithmsAndDataStructureUsingPythonZhongwenban/font/fontello.ttf
ProblemSolvingWithAlgorithmsAndDataStructureUsingPythonZhongwenban/font/fontello.woff
ProblemSolvingWithAlgorithmsAndDataStructureUsingPythonZhongwenban/img/__init__.py
ProblemSolvingWithAlgorithmsAndDataStructureUsingPythonZhongwenban/img/annotator-glyph-sprite.png
ProblemSolvingWithAlgorithmsAndDataStructureUsingPythonZhongwenban/img/annotator-icon-sprite.png
ProblemSolvingWithAlgorithmsAndDataStructureUsingPythonZhongwenban/img/apple-touch-icon.png
ProblemSolvingWithAlgorithmsAndDataStructureUsingPythonZhongwenban/img/cancelfullscreen.png
ProblemSolvingWithAlgorithmsAndDataStructureUsingPythonZhongwenban/img/close.png
ProblemSolvingWithAlgorithmsAndDataStructureUsingPythonZhongwenban/img/fullscreen.png
ProblemSolvingWithAlgorithmsAndDataStructureUsingPythonZhongwenban/img/loader.gif
problem_solving_with_algorithms_and_data_structure_using_python_zhongwenban-2024.3.2.0.dist-info/METADATA
problem_solving_with_algorithms_and_data_structure_using_python_zhongwenban-2024.3.2.0.dist-info/WHEEL
problem_solving_with_algorithms_and_data_structure_using_python_zhongwenban-2024.3.2.0.dist-info/entry_points.txt
problem_solving_with_algorithms_and_data_structure_using_python_zhongwenban-2024.3.2.0.dist-info/top_level.txt
problem_solving_with_algorithms_and_data_structure_using_python_zhongwenban-2024.3.2.0.dist-info/RECORD
